exlib/__init__.py
exlib/datasets/__init__.py
exlib/datasets/chestx.py
exlib/datasets/cholec.py
exlib/datasets/common.py
exlib/datasets/cosmogrid.py
exlib/datasets/dataset_preprocess_raw.py
exlib/datasets/emotion.py
exlib/datasets/emotion_helper.py
exlib/datasets/eraser_movies.py
exlib/datasets/informer_models.py
exlib/datasets/mass_maps.py
exlib/datasets/multilingual_politeness.py
exlib/datasets/mvtec.py
exlib/datasets/politeness_helper.py
exlib/datasets/pretrain.py
exlib/datasets/supernova.py
exlib/datasets/supernova_helper.py
exlib/datasets/timeseries_anomalies.py
exlib/datasets/visa.py
exlib/evaluators/__init__.py
exlib/evaluators/attributions.py
exlib/evaluators/common.py
exlib/evaluators/ins_del.py
exlib/explainers/__init__.py
exlib/explainers/agi.py
exlib/explainers/ampe.py
exlib/explainers/archipelago.py
exlib/explainers/attn.py
exlib/explainers/common.py
exlib/explainers/fullgrad.py
exlib/explainers/gradcam.py
exlib/explainers/idg.py
exlib/explainers/intgrad.py
exlib/explainers/kernelshap.py
exlib/explainers/lime.py
exlib/explainers/mfaba.py
exlib/explainers/patch_intgrad.py
exlib/explainers/pls.py
exlib/explainers/rise.py
exlib/explainers/shap.py
exlib/explainers/libs/archipelago/explainer.py
exlib/explainers/libs/archipelago/application_utils/common_utils.py
exlib/explainers/libs/archipelago/application_utils/image_utils.py
exlib/explainers/libs/archipelago/application_utils/rec_utils.py
exlib/explainers/libs/archipelago/application_utils/text_utils.py
exlib/explainers/libs/archipelago/application_utils/text_utils_tf.py
exlib/explainers/libs/archipelago/application_utils/text_utils_torch.py
exlib/explainers/libs/archipelago/application_utils/utils_torch.py
exlib/explainers/libs/archipelago/viz/colors.py
exlib/explainers/libs/archipelago/viz/rec.py
exlib/explainers/libs/archipelago/viz/text.py
exlib/explainers/libs/craft/__init__.py
exlib/explainers/libs/craft/craft_torch.py
exlib/explainers/libs/fullgrad/saliency/__init__.py
exlib-0.2.1.dist-info/LICENSE
exlib-0.2.1.dist-info/METADATA
exlib-0.2.1.dist-info/WHEEL
exlib-0.2.1.dist-info/top_level.txt
exlib-0.2.1.dist-info/RECORD
