Metadata-Version: 2.1
Name: exlib
Version: 0.2.1
Summary: Toolkit for explainability by BrachioLab
Author-email: Eric Wong <exwong@cis.upenn.edu>, Helen Jin <helenjin@seas.upenn.edu>
Project-URL: Homepage, https://github.com/BrachioLab/exlib
Project-URL: Bug Tracker, https://github.com/BrachioLab/exlib/issues
Classifier: Programming Language :: Python :: 3
Classifier: License :: OSI Approved :: MIT License
Classifier: Operating System :: OS Independent
Requires-Python: >=3.9
License-File: LICENSE
Requires-Dist: lime >=0.2
Requires-Dist: shap >=0.42
Requires-Dist: torch >=2.0
Requires-Dist: torchvision >=0.15
Requires-Dist: grad-cam >=1.4.8
Requires-Dist: jsonlines >=3.1.0
Requires-Dist: scikit-image >=0.22
Requires-Dist: datasets >=2.19
Requires-Dist: transformers >=4.38
Requires-Dist: sentence-transformers >=3.0.0
Requires-Dist: sentencepiece >=0.2.0
Requires-Dist: torchxrayvision >=1.2.3
Requires-Dist: bertopic >=0.16.4
Requires-Dist: segment-anything >=1.0
Requires-Dist: timm >=1.0.10
Requires-Dist: notebook
Requires-Dist: ipywidgets
Provides-Extra: dev
Requires-Dist: notebook ; extra == 'dev'
